pyspark_analyzer/__init__.py
pyspark_analyzer/api.py
pyspark_analyzer/constants.py
pyspark_analyzer/exceptions.py
pyspark_analyzer/logging.py
pyspark_analyzer/performance.py
pyspark_analyzer/profiler.py
pyspark_analyzer/progress.py
pyspark_analyzer/py.typed
pyspark_analyzer/quality.py
pyspark_analyzer/sampling.py
pyspark_analyzer/statistics.py
pyspark_analyzer/utils.py
pyspark_analyzer-5.0.2.dist-info/METADATA
pyspark_analyzer-5.0.2.dist-info/WHEEL
pyspark_analyzer-5.0.2.dist-info/licenses/LICENSE
pyspark_analyzer-5.0.2.dist-info/RECORD
