Metadata-Version: 2.4
Name: pyspark-analyzer
Version: 5.0.2
Summary: A comprehensive PySpark DataFrame profiler for generating detailed statistics and data quality reports
Project-URL: Homepage, https://github.com/bjornvandijkman1993/pyspark-analyzer
Project-URL: Repository, https://github.com/bjornvandijkman1993/pyspark-analyzer
Project-URL: Documentation, https://github.com/bjornvandijkman1993/pyspark-analyzer#readme
Project-URL: Issues, https://github.com/bjornvandijkman1993/pyspark-analyzer/issues
Author-email: Spark Profiler Contributors <bjornvandijkman@gmail.com>
Maintainer-email: Björn van Dijkman <bjornvandijkman@gmail.com>
License: MIT
License-File: LICENSE
Keywords: apache-spark,big-data,data-analysis,data-profiling,data-quality,dataframe,pyspark,spark,statistics
Classifier: Development Status :: 4 - Beta
Classifier: Intended Audience :: Developers
Classifier: License :: OSI Approved :: MIT License
Classifier: Programming Language :: Python :: 3
Classifier: Programming Language :: Python :: 3.8
Classifier: Programming Language :: Python :: 3.9
Classifier: Programming Language :: Python :: 3.10
Classifier: Programming Language :: Python :: 3.11
Classifier: Programming Language :: Python :: 3.12
Classifier: Programming Language :: Python :: 3.13
Classifier: Topic :: Scientific/Engineering :: Information Analysis
Classifier: Topic :: Software Development :: Libraries :: Python Modules
Requires-Python: >=3.8
Requires-Dist: pandas>=1.0.0
Requires-Dist: pyspark>=3.0.0
Provides-Extra: dev
Requires-Dist: bandit[toml]>=1.7.0; extra == 'dev'
Requires-Dist: black>=22.0.0; extra == 'dev'
Requires-Dist: build>=0.8.0; extra == 'dev'
Requires-Dist: cyclonedx-bom>=4.0.0; extra == 'dev'
Requires-Dist: detect-secrets>=1.4.0; extra == 'dev'
Requires-Dist: isort>=5.0.0; extra == 'dev'
Requires-Dist: mypy>=0.900; extra == 'dev'
Requires-Dist: pip-audit>=2.0.0; extra == 'dev'
Requires-Dist: pip-licenses>=4.0.0; extra == 'dev'
Requires-Dist: pytest-cov>=2.0.0; extra == 'dev'
Requires-Dist: pytest>=6.0.0; extra == 'dev'
Requires-Dist: safety>=2.0.0; extra == 'dev'
Requires-Dist: twine>=4.0.0; extra == 'dev'
Provides-Extra: docs
Requires-Dist: myst-parser<4.0.0,>=3.0.0; extra == 'docs'
Requires-Dist: sphinx-autodoc-typehints<2.0.0,>=1.25.3; extra == 'docs'
Requires-Dist: sphinx-rtd-theme>=3.0.0; extra == 'docs'
Requires-Dist: sphinx<8.0.0,>=7.1.0; extra == 'docs'
